<?xml version="1.0" encoding="utf-8"?><content>
	<item>
		<title>珍宝岛</title>
		<url>http://www.php100.com/</url>
		<image>images/1.jpg</image>
		<title2>法国浪漫冒险喜剧</title2>
	</item>
	<item>
		<title>导火线</title>
		<url>http://www.php100.com/</url>
		<image>images/2.jpg</image>
		<title2>迅雷宽频独家网络热播即将开放</title2>
	</item>
	<item>
		<title>哆啦A梦 大雄的新魔界大冒险</title>
		<url>http://www.php100.com/</url>
		<image>images/3.jpg</image>
		<title2>2007年最新日本哆啦A梦剧场版</title2>
	</item>
	<item>
		<title>生死格斗</title>
		<url>http://www.php100.com/</url>
		<image>images/4.jpg</image>
		<title2>全国热映 各国功夫美女云集</title2>
	</item>
	<item>
		<title>突破</title>
		<url>http://www.php100.com/</url>
		<image>images/5.jpg</image>
		<title2>范晓萱独立发行新专辑</title2>
	</item>
	<item>
		<title>黑糖玛奇朵</title>
		<url>http://www.php100.com/</url>
		<image>images/6.jpg</image>
		<title2>黑社会美眉＋棒棒糖男孩</title2>
	</item>
	<item>
		<title>父女七日变</title>
		<url>http://www.php100.com/</url>
		<image>images/7.jpg</image>
		<title2>身体互换 女儿禁止老爸偷看洗澡</title2>
	</item>
	<item>
		<title>我要变成硬柿子</title>
		<url>http://www.php100.com/</url>
		<image>images/8.jpg</image>
		<title2>看软弱男生如何成为恋爱杀手</title2>
	</item>
	<item>
		<title>终极一家</title>
		<url>http://www.php100.com/</url>
		<image>images/9.jpg</image>
		<title2>终极一班原班人马最新奉献</title2>
	</item>
</content>